{
	"configurations" : 
	[
		{
			"directories" : 
			[
				{
					"build" : ".",
					"jsonFile" : "directory-.-Debug-f5ebdc15457944623624.json",
					"minimumCMakeVersion" : 
					{
						"string" : "3.5"
					},
					"projectIndex" : 0,
					"source" : ".",
					"targetIndexes" : 
					[
						0,
						1,
						2
					]
				}
			],
			"name" : "Debug",
			"projects" : 
			[
				{
					"directoryIndexes" : 
					[
						0
					],
					"name" : "CSystem-Qt6",
					"targetIndexes" : 
					[
						0,
						1,
						2
					]
				}
			],
			"targets" : 
			[
				{
					"directoryIndex" : 0,
					"id" : "CSystem-Qt6::@6890427a1f51a3e7e1df",
					"jsonFile" : "target-CSystem-Qt6-Debug-7c687ad24a06d5591ce6.json",
					"name" : "CSystem-Qt6",
					"projectIndex" : 0
				},
				{
					"directoryIndex" : 0,
					"id" : "CSystem-Qt6_autogen::@6890427a1f51a3e7e1df",
					"jsonFile" : "target-CSystem-Qt6_autogen-Debug-edba24ddc06279684cb2.json",
					"name" : "CSystem-Qt6_autogen",
					"projectIndex" : 0
				},
				{
					"directoryIndex" : 0,
					"id" : "CSystem-Qt6_autogen_timestamp_deps::@6890427a1f51a3e7e1df",
					"jsonFile" : "target-CSystem-Qt6_autogen_timestamp_deps-Debug-f7d7678c4ad451c3d586.json",
					"name" : "CSystem-Qt6_autogen_timestamp_deps",
					"projectIndex" : 0
				}
			]
		}
	],
	"kind" : "codemodel",
	"paths" : 
	{
		"build" : "/home/stvsl/Documents/\u4e2a\u4eba\u9879\u76ee/CSystem-Qt6/CSystem-Qt6/build",
		"source" : "/home/stvsl/Documents/\u4e2a\u4eba\u9879\u76ee/CSystem-Qt6/CSystem-Qt6"
	},
	"version" : 
	{
		"major" : 2,
		"minor" : 3
	}
}
